{
  "inputs": {
    "src/dev.ts": {
      "bytes": 459,
      "imports": [],
      "format": "esm"
    },
    "src/g.ts": {
      "bytes": 4548,
      "imports": [
        {
          "path": "@monochromatic.dev/module-fs-path",
          "kind": "import-statement",
          "external": true
        },
        {
          "path": "glob",
          "kind": "import-statement",
          "external": true
        },
        {
          "path": "rambdax",
          "kind": "import-statement",
          "external": true
        },
        {
          "path": "<runtime>",
          "kind": "import-statement",
          "external": true
        }
      ],
      "format": "esm"
    },
    "src/dts.ts": {
      "bytes": 639,
      "imports": [
        {
          "path": "@monochromatic.dev/module-console",
          "kind": "import-statement",
          "external": true
        },
        {
          "path": "@monochromatic.dev/module-fs-path",
          "kind": "import-statement",
          "external": true
        },
        {
          "path": "zx",
          "kind": "import-statement",
          "external": true
        },
        {
          "path": "src/g.ts",
          "kind": "import-statement",
          "original": "./g.ts"
        },
        {
          "path": "<runtime>",
          "kind": "import-statement",
          "external": true
        }
      ],
      "format": "esm"
    },
    "src/state.ts": {
      "bytes": 174,
      "imports": [],
      "format": "esm"
    },
    "src/br.ts": {
      "bytes": 748,
      "imports": [
        {
          "path": "@monochromatic.dev/module-console",
          "kind": "import-statement",
          "external": true
        },
        {
          "path": "@monochromatic.dev/module-fs-path",
          "kind": "import-statement",
          "external": true
        },
        {
          "path": "glob",
          "kind": "import-statement",
          "external": true
        },
        {
          "path": "rambdax",
          "kind": "import-statement",
          "external": true
        },
        {
          "path": "zx",
          "kind": "import-statement",
          "external": true
        },
        {
          "path": "src/state.ts",
          "kind": "import-statement",
          "original": "./state.ts"
        },
        {
          "path": "src/g.ts",
          "kind": "import-statement",
          "original": "./g.ts"
        },
        {
          "path": "<runtime>",
          "kind": "import-statement",
          "external": true
        }
      ],
      "format": "esm"
    },
    "src/caddy.ts": {
      "bytes": 1667,
      "imports": [
        {
          "path": "@monochromatic.dev/module-console",
          "kind": "import-statement",
          "external": true
        },
        {
          "path": "@monochromatic.dev/module-fs-path",
          "kind": "import-statement",
          "external": true
        },
        {
          "path": "<runtime>",
          "kind": "import-statement",
          "external": true
        }
      ],
      "format": "esm"
    },
    "src/css.ts": {
      "bytes": 3413,
      "imports": [
        {
          "path": "@monochromatic.dev/lightningcss-plugin-apply",
          "kind": "import-statement",
          "external": true
        },
        {
          "path": "@monochromatic.dev/lightningcss-plugin-custom-units",
          "kind": "import-statement",
          "external": true
        },
        {
          "path": "@monochromatic.dev/lightningcss-plugin-property-lookup",
          "kind": "import-statement",
          "external": true
        },
        {
          "path": "@monochromatic.dev/lightningcss-plugin-size",
          "kind": "import-statement",
          "external": true
        },
        {
          "path": "@monochromatic.dev/module-console",
          "kind": "import-statement",
          "external": true
        },
        {
          "path": "@monochromatic.dev/module-fs-path",
          "kind": "import-statement",
          "external": true
        },
        {
          "path": "@monochromatic.dev/module-resolve",
          "kind": "import-statement",
          "external": true
        },
        {
          "path": "browserslist",
          "kind": "import-statement",
          "external": true
        },
        {
          "path": "cssnano",
          "kind": "import-statement",
          "external": true
        },
        {
          "path": "cssnano-preset-advanced",
          "kind": "import-statement",
          "external": true
        },
        {
          "path": "lightningcss",
          "kind": "import-statement",
          "external": true
        },
        {
          "path": "lightningcss",
          "kind": "import-statement",
          "external": true
        },
        {
          "path": "postcss",
          "kind": "import-statement",
          "external": true
        },
        {
          "path": "rambdax",
          "kind": "import-statement",
          "external": true
        },
        {
          "path": "src/g.ts",
          "kind": "import-statement",
          "original": "./g.ts"
        },
        {
          "path": "<runtime>",
          "kind": "import-statement",
          "external": true
        }
      ],
      "format": "esm"
    },
    "src/rehype.ts": {
      "bytes": 940,
      "imports": [
        {
          "path": "hast-util-from-html",
          "kind": "import-statement",
          "external": true
        },
        {
          "path": "hast-util-to-html",
          "kind": "import-statement",
          "external": true
        },
        {
          "path": "rambdax",
          "kind": "import-statement",
          "external": true
        },
        {
          "path": "rehype-remove-comments",
          "kind": "import-statement",
          "external": true
        },
        {
          "path": "unified",
          "kind": "import-statement",
          "external": true
        },
        {
          "path": "<runtime>",
          "kind": "import-statement",
          "external": true
        }
      ],
      "format": "esm"
    },
    "src/cp.ts": {
      "bytes": 1750,
      "imports": [
        {
          "path": "@monochromatic.dev/module-console",
          "kind": "import-statement",
          "external": true
        },
        {
          "path": "@monochromatic.dev/module-fs-path",
          "kind": "import-statement",
          "external": true
        },
        {
          "path": "rambdax",
          "kind": "import-statement",
          "external": true
        },
        {
          "path": "src/g.ts",
          "kind": "import-statement",
          "original": "./g.ts"
        },
        {
          "path": "<runtime>",
          "kind": "import-statement",
          "external": true
        }
      ],
      "format": "esm"
    },
    "src/image.ts": {
      "bytes": 3210,
      "imports": [
        {
          "path": "@monochromatic.dev/module-fs-path",
          "kind": "import-statement",
          "external": true
        },
        {
          "path": "rambdax",
          "kind": "import-statement",
          "external": true
        },
        {
          "path": "sharp",
          "kind": "import-statement",
          "external": true
        },
        {
          "path": "svgo",
          "kind": "import-statement",
          "external": true
        },
        {
          "path": "zx",
          "kind": "import-statement",
          "external": true
        },
        {
          "path": "<runtime>",
          "kind": "import-statement",
          "external": true
        }
      ],
      "format": "esm"
    },
    "src/favicon.ts": {
      "bytes": 6132,
      "imports": [
        {
          "path": "@monochromatic.dev/module-console",
          "kind": "import-statement",
          "external": true
        },
        {
          "path": "@monochromatic.dev/module-fs-path",
          "kind": "import-statement",
          "external": true
        },
        {
          "path": "@monochromatic.dev/module-is-lang",
          "kind": "import-statement",
          "external": true
        },
        {
          "path": "glob",
          "kind": "import-statement",
          "external": true
        },
        {
          "path": "rambdax",
          "kind": "import-statement",
          "external": true
        },
        {
          "path": "smol-toml",
          "kind": "import-statement",
          "external": true
        },
        {
          "path": "zx",
          "kind": "import-statement",
          "external": true
        },
        {
          "path": "src/g.ts",
          "kind": "import-statement",
          "original": "./g.ts"
        },
        {
          "path": "src/image.ts",
          "kind": "import-statement",
          "original": "./image.ts"
        },
        {
          "path": "<runtime>",
          "kind": "import-statement",
          "external": true
        }
      ],
      "format": "esm"
    },
    "src/external.ts": {
      "bytes": 3440,
      "imports": [
        {
          "path": "@logtape/logtape",
          "kind": "import-statement",
          "external": true
        }
      ],
      "format": "esm"
    },
    "src/js.ts": {
      "bytes": 5610,
      "imports": [
        {
          "path": "@hbsnow/rehype-sectionize",
          "kind": "import-statement",
          "external": true
        },
        {
          "path": "@mdx-js/esbuild",
          "kind": "import-statement",
          "external": true
        },
        {
          "path": "@monochromatic.dev/esbuild-plugin-jsonc",
          "kind": "import-statement",
          "external": true
        },
        {
          "path": "@monochromatic.dev/esbuild-plugin-toml",
          "kind": "import-statement",
          "external": true
        },
        {
          "path": "@monochromatic.dev/esbuild-plugin-vue",
          "kind": "import-statement",
          "external": true
        },
        {
          "path": "@monochromatic.dev/esbuild-plugin-yaml",
          "kind": "import-statement",
          "external": true
        },
        {
          "path": "@monochromatic.dev/schema-theme-consts",
          "kind": "import-statement",
          "external": true
        },
        {
          "path": "browserslist",
          "kind": "import-statement",
          "external": true
        },
        {
          "path": "esbuild",
          "kind": "import-statement",
          "external": true
        },
        {
          "path": "esbuild-plugin-browserslist",
          "kind": "import-statement",
          "external": true
        },
        {
          "path": "remark-gfm",
          "kind": "import-statement",
          "external": true
        },
        {
          "path": "remark-github-beta-blockquote-admonitions",
          "kind": "import-statement",
          "external": true
        },
        {
          "path": "remark-smartypants",
          "kind": "import-statement",
          "external": true
        },
        {
          "path": "rehype-highlight",
          "kind": "import-statement",
          "external": true
        },
        {
          "path": "rambdax",
          "kind": "import-statement",
          "external": true
        },
        {
          "path": "@monochromatic.dev/module-console",
          "kind": "import-statement",
          "external": true
        },
        {
          "path": "@monochromatic.dev/module-fs-path",
          "kind": "import-statement",
          "external": true
        },
        {
          "path": "src/dev.ts",
          "kind": "import-statement",
          "original": "./dev.ts"
        },
        {
          "path": "src/external.ts",
          "kind": "import-statement",
          "original": "./external.ts"
        },
        {
          "path": "src/g.ts",
          "kind": "import-statement",
          "original": "./g.ts"
        },
        {
          "path": "highlight.js/lib/languages/bash",
          "kind": "import-statement",
          "external": true
        },
        {
          "path": "highlight.js/lib/languages/css",
          "kind": "import-statement",
          "external": true
        },
        {
          "path": "highlight.js/lib/languages/xml",
          "kind": "import-statement",
          "external": true
        },
        {
          "path": "highlight.js/lib/languages/ini",
          "kind": "import-statement",
          "external": true
        },
        {
          "path": "highlight.js/lib/languages/javascript",
          "kind": "import-statement",
          "external": true
        },
        {
          "path": "highlight.js/lib/languages/json",
          "kind": "import-statement",
          "external": true
        },
        {
          "path": "highlight.js/lib/languages/markdown",
          "kind": "import-statement",
          "external": true
        },
        {
          "path": "highlight.js/lib/languages/plaintext",
          "kind": "import-statement",
          "external": true
        },
        {
          "path": "highlight.js/lib/languages/yaml",
          "kind": "import-statement",
          "external": true
        },
        {
          "path": "highlight.js/lib/languages/yaml",
          "kind": "import-statement",
          "external": true
        },
        {
          "path": "<runtime>",
          "kind": "import-statement",
          "external": true
        }
      ],
      "format": "esm"
    },
    "src/vue.ts": {
      "bytes": 4078,
      "imports": [
        {
          "path": "@monochromatic.dev/module-console",
          "kind": "import-statement",
          "external": true
        },
        {
          "path": "@monochromatic.dev/module-fs-path",
          "kind": "import-statement",
          "external": true
        },
        {
          "path": "esbuild",
          "kind": "import-statement",
          "external": true
        },
        {
          "path": "zx",
          "kind": "import-statement",
          "external": true
        },
        {
          "path": "src/g.ts",
          "kind": "import-statement",
          "original": "./g.ts"
        },
        {
          "path": "src/js.ts",
          "kind": "import-statement",
          "original": "./js.ts"
        },
        {
          "path": "<runtime>",
          "kind": "import-statement",
          "external": true
        }
      ],
      "format": "esm"
    },
    "src/html.ts": {
      "bytes": 2181,
      "imports": [
        {
          "path": "@monochromatic.dev/module-console",
          "kind": "import-statement",
          "external": true
        },
        {
          "path": "@monochromatic.dev/module-fs-path",
          "kind": "import-statement",
          "external": true
        },
        {
          "path": "glob",
          "kind": "import-statement",
          "external": true
        },
        {
          "path": "rambdax",
          "kind": "import-statement",
          "external": true
        },
        {
          "path": "src/rehype.ts",
          "kind": "import-statement",
          "original": "./rehype.ts"
        },
        {
          "path": "src/cp.ts",
          "kind": "import-statement",
          "original": "./cp.ts"
        },
        {
          "path": "src/favicon.ts",
          "kind": "import-statement",
          "original": "./favicon.ts"
        },
        {
          "path": "src/g.ts",
          "kind": "import-statement",
          "original": "./g.ts"
        },
        {
          "path": "src/vue.ts",
          "kind": "import-statement",
          "original": "./vue.ts"
        },
        {
          "path": "<runtime>",
          "kind": "import-statement",
          "external": true
        }
      ],
      "format": "esm"
    },
    "src/staticAndCompress.ts": {
      "bytes": 596,
      "imports": [
        {
          "path": "@logtape/logtape",
          "kind": "import-statement",
          "external": true
        },
        {
          "path": "src/br.ts",
          "kind": "import-statement",
          "original": "./br.ts"
        },
        {
          "path": "src/caddy.ts",
          "kind": "import-statement",
          "original": "./caddy.ts"
        },
        {
          "path": "src/css.ts",
          "kind": "import-statement",
          "original": "./css.ts"
        },
        {
          "path": "src/html.ts",
          "kind": "import-statement",
          "original": "./html.ts"
        },
        {
          "path": "src/js.ts",
          "kind": "import-statement",
          "original": "./js.ts"
        },
        {
          "path": "<runtime>",
          "kind": "import-statement",
          "external": true
        }
      ],
      "format": "esm"
    },
    "src/child.ts": {
      "bytes": 1145,
      "imports": [
        {
          "path": "@monochromatic.dev/module-fs-path",
          "kind": "import-statement",
          "external": true
        },
        {
          "path": "@monochromatic.dev/module-pm",
          "kind": "import-statement",
          "external": true
        },
        {
          "path": "node:child_process",
          "kind": "import-statement",
          "external": true
        },
        {
          "path": "node:util",
          "kind": "import-statement",
          "external": true
        },
        {
          "path": "<runtime>",
          "kind": "import-statement",
          "external": true
        }
      ],
      "format": "esm"
    },
    "src/index.ts": {
      "bytes": 2371,
      "imports": [
        {
          "path": "@monochromatic.dev/module-fs-path",
          "kind": "import-statement",
          "external": true
        },
        {
          "path": "zod",
          "kind": "import-statement",
          "external": true
        },
        {
          "path": "zod-opts",
          "kind": "import-statement",
          "external": true
        },
        {
          "path": "zx",
          "kind": "import-statement",
          "external": true
        },
        {
          "path": "rambdax",
          "kind": "import-statement",
          "external": true
        },
        {
          "path": "jsonc-simple-parser",
          "kind": "import-statement",
          "external": true
        },
        {
          "path": "@monochromatic.dev/module-console",
          "kind": "import-statement",
          "external": true
        },
        {
          "path": "src/dev.ts",
          "kind": "import-statement",
          "original": "./dev.ts"
        },
        {
          "path": "src/dts.ts",
          "kind": "import-statement",
          "original": "./dts.ts"
        },
        {
          "path": "src/staticAndCompress.ts",
          "kind": "import-statement",
          "original": "./staticAndCompress.ts"
        },
        {
          "path": "src/child.ts",
          "kind": "import-statement",
          "original": "./child.ts"
        },
        {
          "path": "@logtape/logtape",
          "kind": "import-statement",
          "external": true
        }
      ],
      "format": "esm"
    }
  },
  "outputs": {
    "dist/final/index.js.map": {
      "imports": [],
      "exports": [],
      "inputs": {},
      "bytes": 69097
    },
    "dist/final/index.js": {
      "imports": [
        {
          "path": "@monochromatic.dev/module-fs-path",
          "kind": "import-statement",
          "external": true
        },
        {
          "path": "zod",
          "kind": "import-statement",
          "external": true
        },
        {
          "path": "zod-opts",
          "kind": "import-statement",
          "external": true
        },
        {
          "path": "zx",
          "kind": "import-statement",
          "external": true
        },
        {
          "path": "rambdax",
          "kind": "import-statement",
          "external": true
        },
        {
          "path": "jsonc-simple-parser",
          "kind": "import-statement",
          "external": true
        },
        {
          "path": "@monochromatic.dev/module-console",
          "kind": "import-statement",
          "external": true
        },
        {
          "path": "@monochromatic.dev/module-console",
          "kind": "import-statement",
          "external": true
        },
        {
          "path": "@monochromatic.dev/module-fs-path",
          "kind": "import-statement",
          "external": true
        },
        {
          "path": "zx",
          "kind": "import-statement",
          "external": true
        },
        {
          "path": "@monochromatic.dev/module-fs-path",
          "kind": "import-statement",
          "external": true
        },
        {
          "path": "glob",
          "kind": "import-statement",
          "external": true
        },
        {
          "path": "rambdax",
          "kind": "import-statement",
          "external": true
        },
        {
          "path": "@logtape/logtape",
          "kind": "import-statement",
          "external": true
        },
        {
          "path": "@monochromatic.dev/module-console",
          "kind": "import-statement",
          "external": true
        },
        {
          "path": "@monochromatic.dev/module-fs-path",
          "kind": "import-statement",
          "external": true
        },
        {
          "path": "glob",
          "kind": "import-statement",
          "external": true
        },
        {
          "path": "rambdax",
          "kind": "import-statement",
          "external": true
        },
        {
          "path": "zx",
          "kind": "import-statement",
          "external": true
        },
        {
          "path": "@monochromatic.dev/module-console",
          "kind": "import-statement",
          "external": true
        },
        {
          "path": "@monochromatic.dev/module-fs-path",
          "kind": "import-statement",
          "external": true
        },
        {
          "path": "@monochromatic.dev/lightningcss-plugin-apply",
          "kind": "import-statement",
          "external": true
        },
        {
          "path": "@monochromatic.dev/lightningcss-plugin-custom-units",
          "kind": "import-statement",
          "external": true
        },
        {
          "path": "@monochromatic.dev/lightningcss-plugin-property-lookup",
          "kind": "import-statement",
          "external": true
        },
        {
          "path": "@monochromatic.dev/lightningcss-plugin-size",
          "kind": "import-statement",
          "external": true
        },
        {
          "path": "@monochromatic.dev/module-console",
          "kind": "import-statement",
          "external": true
        },
        {
          "path": "@monochromatic.dev/module-fs-path",
          "kind": "import-statement",
          "external": true
        },
        {
          "path": "@monochromatic.dev/module-resolve",
          "kind": "import-statement",
          "external": true
        },
        {
          "path": "browserslist",
          "kind": "import-statement",
          "external": true
        },
        {
          "path": "cssnano",
          "kind": "import-statement",
          "external": true
        },
        {
          "path": "cssnano-preset-advanced",
          "kind": "import-statement",
          "external": true
        },
        {
          "path": "lightningcss",
          "kind": "import-statement",
          "external": true
        },
        {
          "path": "lightningcss",
          "kind": "import-statement",
          "external": true
        },
        {
          "path": "postcss",
          "kind": "import-statement",
          "external": true
        },
        {
          "path": "rambdax",
          "kind": "import-statement",
          "external": true
        },
        {
          "path": "@monochromatic.dev/module-console",
          "kind": "import-statement",
          "external": true
        },
        {
          "path": "@monochromatic.dev/module-fs-path",
          "kind": "import-statement",
          "external": true
        },
        {
          "path": "glob",
          "kind": "import-statement",
          "external": true
        },
        {
          "path": "rambdax",
          "kind": "import-statement",
          "external": true
        },
        {
          "path": "hast-util-from-html",
          "kind": "import-statement",
          "external": true
        },
        {
          "path": "hast-util-to-html",
          "kind": "import-statement",
          "external": true
        },
        {
          "path": "rambdax",
          "kind": "import-statement",
          "external": true
        },
        {
          "path": "rehype-remove-comments",
          "kind": "import-statement",
          "external": true
        },
        {
          "path": "unified",
          "kind": "import-statement",
          "external": true
        },
        {
          "path": "@monochromatic.dev/module-console",
          "kind": "import-statement",
          "external": true
        },
        {
          "path": "@monochromatic.dev/module-fs-path",
          "kind": "import-statement",
          "external": true
        },
        {
          "path": "rambdax",
          "kind": "import-statement",
          "external": true
        },
        {
          "path": "@monochromatic.dev/module-console",
          "kind": "import-statement",
          "external": true
        },
        {
          "path": "@monochromatic.dev/module-fs-path",
          "kind": "import-statement",
          "external": true
        },
        {
          "path": "@monochromatic.dev/module-is-lang",
          "kind": "import-statement",
          "external": true
        },
        {
          "path": "glob",
          "kind": "import-statement",
          "external": true
        },
        {
          "path": "rambdax",
          "kind": "import-statement",
          "external": true
        },
        {
          "path": "smol-toml",
          "kind": "import-statement",
          "external": true
        },
        {
          "path": "zx",
          "kind": "import-statement",
          "external": true
        },
        {
          "path": "@monochromatic.dev/module-fs-path",
          "kind": "import-statement",
          "external": true
        },
        {
          "path": "rambdax",
          "kind": "import-statement",
          "external": true
        },
        {
          "path": "sharp",
          "kind": "import-statement",
          "external": true
        },
        {
          "path": "svgo",
          "kind": "import-statement",
          "external": true
        },
        {
          "path": "zx",
          "kind": "import-statement",
          "external": true
        },
        {
          "path": "@monochromatic.dev/module-console",
          "kind": "import-statement",
          "external": true
        },
        {
          "path": "@monochromatic.dev/module-fs-path",
          "kind": "import-statement",
          "external": true
        },
        {
          "path": "esbuild",
          "kind": "import-statement",
          "external": true
        },
        {
          "path": "zx",
          "kind": "import-statement",
          "external": true
        },
        {
          "path": "@hbsnow/rehype-sectionize",
          "kind": "import-statement",
          "external": true
        },
        {
          "path": "@mdx-js/esbuild",
          "kind": "import-statement",
          "external": true
        },
        {
          "path": "@monochromatic.dev/esbuild-plugin-jsonc",
          "kind": "import-statement",
          "external": true
        },
        {
          "path": "@monochromatic.dev/esbuild-plugin-toml",
          "kind": "import-statement",
          "external": true
        },
        {
          "path": "@monochromatic.dev/esbuild-plugin-vue",
          "kind": "import-statement",
          "external": true
        },
        {
          "path": "@monochromatic.dev/esbuild-plugin-yaml",
          "kind": "import-statement",
          "external": true
        },
        {
          "path": "@monochromatic.dev/schema-theme-consts",
          "kind": "import-statement",
          "external": true
        },
        {
          "path": "browserslist",
          "kind": "import-statement",
          "external": true
        },
        {
          "path": "esbuild",
          "kind": "import-statement",
          "external": true
        },
        {
          "path": "esbuild-plugin-browserslist",
          "kind": "import-statement",
          "external": true
        },
        {
          "path": "remark-gfm",
          "kind": "import-statement",
          "external": true
        },
        {
          "path": "remark-github-beta-blockquote-admonitions",
          "kind": "import-statement",
          "external": true
        },
        {
          "path": "remark-smartypants",
          "kind": "import-statement",
          "external": true
        },
        {
          "path": "rehype-highlight",
          "kind": "import-statement",
          "external": true
        },
        {
          "path": "rambdax",
          "kind": "import-statement",
          "external": true
        },
        {
          "path": "@monochromatic.dev/module-console",
          "kind": "import-statement",
          "external": true
        },
        {
          "path": "@monochromatic.dev/module-fs-path",
          "kind": "import-statement",
          "external": true
        },
        {
          "path": "@logtape/logtape",
          "kind": "import-statement",
          "external": true
        },
        {
          "path": "highlight.js/lib/languages/bash",
          "kind": "import-statement",
          "external": true
        },
        {
          "path": "highlight.js/lib/languages/css",
          "kind": "import-statement",
          "external": true
        },
        {
          "path": "highlight.js/lib/languages/xml",
          "kind": "import-statement",
          "external": true
        },
        {
          "path": "highlight.js/lib/languages/ini",
          "kind": "import-statement",
          "external": true
        },
        {
          "path": "highlight.js/lib/languages/javascript",
          "kind": "import-statement",
          "external": true
        },
        {
          "path": "highlight.js/lib/languages/json",
          "kind": "import-statement",
          "external": true
        },
        {
          "path": "highlight.js/lib/languages/markdown",
          "kind": "import-statement",
          "external": true
        },
        {
          "path": "highlight.js/lib/languages/plaintext",
          "kind": "import-statement",
          "external": true
        },
        {
          "path": "highlight.js/lib/languages/yaml",
          "kind": "import-statement",
          "external": true
        },
        {
          "path": "highlight.js/lib/languages/yaml",
          "kind": "import-statement",
          "external": true
        },
        {
          "path": "@monochromatic.dev/module-fs-path",
          "kind": "import-statement",
          "external": true
        },
        {
          "path": "@monochromatic.dev/module-pm",
          "kind": "import-statement",
          "external": true
        },
        {
          "path": "node:child_process",
          "kind": "import-statement",
          "external": true
        },
        {
          "path": "node:util",
          "kind": "import-statement",
          "external": true
        },
        {
          "path": "@logtape/logtape",
          "kind": "import-statement",
          "external": true
        }
      ],
      "exports": [],
      "entryPoint": "src/index.ts",
      "inputs": {
        "src/index.ts": {
          "bytesInOutput": 2258
        },
        "src/dev.ts": {
          "bytesInOutput": 422
        },
        "src/dts.ts": {
          "bytesInOutput": 557
        },
        "src/g.ts": {
          "bytesInOutput": 4063
        },
        "src/staticAndCompress.ts": {
          "bytesInOutput": 455
        },
        "src/br.ts": {
          "bytesInOutput": 758
        },
        "src/caddy.ts": {
          "bytesInOutput": 1716
        },
        "src/css.ts": {
          "bytesInOutput": 3222
        },
        "src/html.ts": {
          "bytesInOutput": 2115
        },
        "src/rehype.ts": {
          "bytesInOutput": 872
        },
        "src/cp.ts": {
          "bytesInOutput": 1901
        },
        "src/favicon.ts": {
          "bytesInOutput": 6076
        },
        "src/image.ts": {
          "bytesInOutput": 1273
        },
        "src/vue.ts": {
          "bytesInOutput": 3955
        },
        "src/js.ts": {
          "bytesInOutput": 5370
        },
        "src/external.ts": {
          "bytesInOutput": 3349
        },
        "src/child.ts": {
          "bytesInOutput": 1019
        }
      },
      "bytes": 39974
    }
  }
}
